{"60:1:1":{"w":"يٰٓأَيُّهَا","m":"O you (addressing a group)","p":{"يٰٓ":["O"],"أَيُّ":["you"],"هَا":["(addressing a group)"]}},"60:1:2":{"w":"ٱلَّذِينَ","m":"those who (describes ءَامَنُوا۟ - they believed)","p":{"ٱلَّذِي":["those who"],"نَ":["(describes ءَامَنُوا۟ - they believed)"]}},"60:1:3":{"w":"ءَامَنُوا۟","m":"they believed","p":{"ءَامَن":["believed"],"ُوا":["they"]}},"60:1:4":{"w":"لَا","m":"no/not (negates تَتَّخِذُوا۟)","p":{"لَا":["no/not"]}},"60:1:5":{"w":"تَتَّخِذُوا","m":"you (all) take/adopt (as a command after لا)","p":{"تَ":["you"],"تَّخِذ":["take/adopt"],"وا":["(all)"]}},"60:1:6":{"w":"عَدُوِّى","m":"my enemy","p":{"عَدُوّ":["enemy"],"ى":["my"]}},"60:1:7":{"w":"وَعَدُوَّكُمْ","m":"and your enemy","p":{"وَ":["and"],"عَدُوَّ":["enemy"],"كُمْ":["your"]}},"60:1:8":{"w":"أَوْلِيَآءَ","m":"close protecting friends/allies (as objects of لَا تَتَّخِذُوا - do not take)","p":{"أَوْلِيَآءَ":["close protecting friends/allies"],"َ":["(as objects of لَا تَتَّخِذُوا - do not take)"]}},"60:1:9":{"w":"تُلْقُونَ","m":"you (all) throw","p":{"تُ":["you"],"لْقُ":["throw"],"ونَ":["(all)"]}},"60:1:10":{"w":"إِلَيْهِم","m":"to them (referring to the enemies mentioned earlier in the ayah)","p":{"إِلَيْ":["to"],"هِم":["them"]}},"60:1:11":{"w":"بِٱلْمَوَدَّةِ","m":"with the love/affection","p":{"بِ":["with"],"ٱلْ":["the"],"مَوَدَّةِ":["love/affection"]}},"60:1:12":{"w":"وَقَدْ","m":"and indeed","p":{"وَ":["and"],"قَدْ":["indeed"]}},"60:1:13":{"w":"كَفَرُوا","m":"they disbelieved","p":{"كَفَر":["disbelieved"],"ُوا":["they"]}},"60:1:14":{"w":"بِمَا","m":"with what/with that which (connects to كَفَرُوا)","p":{"بِ":["with"],"مَا":["what/that which (connects to كَفَرُوا)"]}},"60:1:15":{"w":"جَآءَكُم","m":"he came to you all","p":{"جَآءَ":["he came"],"كُم":["to you all"]}},"60:1:16":{"w":"مِّنَ","m":"from the (connects to الْحَقِّ)","p":{"مِّنَ":["from"],"َ":["the"]}},"60:1:17":{"w":"ٱلْحَقِّ","m":"the truth (from مِنَ - from)","p":{"ٱلْ":["the"],"حَقِّ":["truth"]}},"60:1:18":{"w":"يُخْرِجُونَ","m":"they make (something/someone) exit","p":{"يُ":["they"],"خْرِجُ":["make exit"],"ونَ":["they"]}},"60:1:19":{"w":"ٱلرَّسُولَ","m":"the messenger (as object of يُخْرِجُونَ - they expel)","p":{"ٱل":["the"],"رَّسُولَ":["messenger"],"َ":["(as object of يُخْرِجُونَ - they expel)"]}},"60:1:20":{"w":"وَإِيَّاكُمْ","m":"and specifically you all","p":{"وَ":["and"],"إِيَّا":["specifically"],"كُمْ":["you all"]}},"60:1:21":{"w":"أَن","m":"that (introduces the verb تُؤْمِنُوا)","p":{"أَ":["that"],"ن":["(connects to next word)"]}},"60:1:22":{"w":"تُؤْمِنُوا۟","m":"you (all) believe","p":{"تُ":["you"],"ؤْمِنُ":["believe"],"وا":["(all)"]}},"60:1:23":{"w":"بِٱللَّهِ","m":"in/by/with Allah","p":{"بِ":["in/by/with"],"ٱللَّهِ":["Allah"]}},"60:1:24":{"w":"رَبِّكُمْ","m":"your (plural) Lord","p":{"رَبِّ":["Lord"],"كُمْ":["your (plural)"]}},"60:1:25":{"w":"إِن","m":"if","p":{"إِن":["if"]}},"60:1:26":{"w":"كُنتُمْ","m":"you all were","p":{"كُن":["were"],"تُ":["you"],"مْ":["all"]}},"60:1:27":{"w":"خَرَجْتُمْ","m":"you all exited","p":{"خَرَجْ":["exited"],"تُ":["you"],"مْ":["all"]}},"60:1:28":{"w":"جِهٰدًا","m":"striving (as the object being done)","p":{"جِهٰد":["striving"],"ًا":["(as the object being done)"]}},"60:1:29":{"w":"فِى","m":"in (preposition affecting سَبِيلِى)","p":{"فِى":["in"]}},"60:1:30":{"w":"سَبِيلِى","m":"my path (in جِهٰدًا فِى سَبِيلِى - striving in my path)","p":{"سَبِيلِ":["path"],"ى":["my"]}},"60:1:31":{"w":"وَٱبْتِغَآءَ","m":"and earnest seeking","p":{"وَ":["and"],"ٱبْتِ":["earnest"],"غَآءَ":["seeking"]}},"60:1:32":{"w":"مَرْضَاتِى","m":"my pleasure (object of ٱبْتِغَآءَ)","p":{"مَرْضَات":["pleasure"],"ى":["my"]}},"60:1:33":{"w":"تُسِرُّونَ","m":"you (all) keep secret","p":{"تُ":["you"],"سِرُّ":["keep secret"],"ونَ":["all"]}},"60:1:34":{"w":"إِلَيْهِم","m":"to them (receiving تُلْقُونَ - you cast/offer)","p":{"إِلَى":["to"],"هِم":["them"]}},"60:1:35":{"w":"بِٱلْمَوَدَّةِ","m":"with the affection (object of تُلْقُونَ)","p":{"بِ":["with"],"ٱلْ":["the"],"مَوَدَّةِ":["affection"]}},"60:1:36":{"w":"وَأَنَا۠","m":"and I","p":{"وَ":["and"],"أَنَا۠":["I"]}},"60:1:37":{"w":"أَعْلَمُ","m":"most knowing (of what you hide)","p":{"أَ":["most"],"عْلَمُ":["knowing"]}},"60:1:38":{"w":"بِمَآ","m":"with what (that came to you from the truth)","p":{"بِ":["with"],"مَآ":["what (that came to you from the truth)"]}},"60:1:39":{"w":"أَخْفَيْتُمْ","m":"you all concealed","p":{"أَ":["concealed"],"خْفَيْ":["concealed"],"تُمْ":["you all"]}},"60:1:40":{"w":"وَمَآ","m":"and what (that was hidden)","p":{"وَ":["and"],"مَآ":["what (that was hidden)"]}},"60:1:41":{"w":"أَعْلَنتُمْ","m":"you (plural) announced","p":{"أَ":["announced"],"عْلَن":["announced"],"تُمْ":["you (plural)"]}},"60:1:43":{"w":"يَفْعَلْهُ","m":"he does it (object of مَن/whoever)","p":{"يَ":["he"],"فْعَلْ":["does"],"هُ":["it"]}},"60:1:44":{"w":"مِنكُمْ","m":"from you all","p":{"مِن":["from"],"كُمْ":["you all"]}},"60:1:45":{"w":"فَقَدْ","m":"then certainly","p":{"فَ":["then"],"قَدْ":["certainly"]}},"60:1:46":{"w":"ضَلَّ","m":"he went far astray (subject of فَقَدْ)","p":{"ضَلَّ":["he went far astray"]}},"60:1:47":{"w":"سَوَآءَ","m":"the straight (path) (describes ٱلسَّبِيلِ)","p":{"سَوَآءَ":["the straight (path)"]}},"60:1:48":{"w":"ٱلسَّبِيلِ","m":"the path/way (being acted upon by فِى)","p":{"ٱل":["the"],"سَّبِيلِ":["path/way"],"ِ":["(being acted upon by فِى)"]}},"60:2:1":{"w":"إِن","m":"if (introduces a condition)","p":{"إِ":["if"],"ن":["introduces a condition"]}},"60:2:2":{"w":"يَثْقَفُوكُمْ","m":"they find/catch you all (followed by يَكُونُوا)","p":{"يَ":["they"],"ثْقَفُ":["find/catch"],"و":["they"],"كُمْ":["you all"]}},"60:2:3":{"w":"يَكُونُوا۟","m":"they are/exist (subject of لَكُمْ أَعْدَآءً - enemies to you)","p":{"يَ":["they"],"كُونُ":["are/exist"],"وا۟":["they"]}},"60:2:4":{"w":"لَكُمْ","m":"for you all/to you all (objects of يَكُونُوا)","p":{"لَ":["for/to"],"كُمْ":["you all"]}},"60:2:5":{"w":"أَعْدَآءً","m":"enemies (as the object of يَكُونُوا)","p":{"أَعْدَآء":["enemies"],"ً":["(as the object of يَكُونُوا)"]}},"60:2:6":{"w":"وَيَبْسُطُوٓا۟","m":"and they spread out (their hands towards you)","p":{"وَ":["and"],"يَ":["they"],"بْسُطُ":["spread out"],"وٓا۟":["they"]}},"60:2:7":{"w":"إِلَيْكُمْ","m":"towards you all/to you all (who are being addressed by the disbelievers)","p":{"إِلَيْ":["towards/to"],"كُمْ":["you all"]}},"60:2:8":{"w":"أَيْدِيَهُمْ","m":"their hands","p":{"أَيْدِيَ":["hands"],"هُمْ":["their"]}},"60:2:9":{"w":"وَأَلْسِنَتَهُم","m":"and their tongues (objects of يَبْسُطُوا - they extend)","p":{"وَ":["and"],"أَلْ":["the"],"سِنَتَ":["tongues"],"هُم":["their"]}},"60:2:10":{"w":"بِٱلسُّوٓءِ","m":"with the evil","p":{"بِ":["with"],"ٱل":["the"],"سُّوٓءِ":["evil"]}},"60:2:11":{"w":"وَوَدُّوا۟","m":"and they wished intensely (for لَوْ تَكْفُرُونَ - if you would disbelieve)","p":{"وَ":["and"],"وَدُّ":["wished intensely"],"وا۟":["they"]}},"60:2:12":{"w":"لَوْ","m":"if only/would that","p":{"لَوْ":["if only/would that"]}},"60:2:13":{"w":"تَكْفُرُونَ","m":"you (all) reject/deny","p":{"تَ":["you"],"كْفُرُ":["reject/deny"],"ونَ":["(all)"]}},"60:3:1":{"w":"لَن","m":"never will","p":{"لَن":["never will"]}},"60:3:2":{"w":"تَنفَعَكُمْ","m":"benefit you all (after لَن)","p":{"تَنفَعَ":["benefit"],"كُمْ":["you all"]}},"60:3:3":{"w":"أَرْحَامُكُمْ","m":"your blood relations/family ties (as subject of تَنفَعَكُمْ)","p":{"أَرْحَامُ":["blood relations/family ties"],"كُمْ":["your"]}},"60:3:4":{"w":"وَلَآ","m":"and not","p":{"وَ":["and"],"لَآ":["not"]}},"60:3:5":{"w":"أَوْلٰدُكُمْ","m":"your children","p":{"أَوْلٰدُ":["children"],"كُمْ":["your"]}},"60:3:6":{"w":"يَوْمَ","m":"day (object of تَنفَعَ - will not benefit)","p":{"يَوْمَ":["day"],"َ":["(object of تَنفَعَ - will not benefit)"]}},"60:3:7":{"w":"ٱلْقِيٰمَةِ","m":"the resurrection (object of يَوْمَ - Day of)","p":{"ٱلْ":["the"],"قِيٰمَةِ":["resurrection"]}},"60:3:8":{"w":"يَفْصِلُ","m":"he separates (between بَيْنَكُمْ - between you all)","p":{"يَ":["he"],"فْصِلُ":["separates"]}},"60:3:9":{"w":"بَيْنَكُمْ","m":"between you all (object of يَفْصِلُ - he separates)","p":{"بَيْنَ":["between"],"كُمْ":["you all"]}},"60:3:10":{"w":"وَٱللَّهُ","m":"and Allah (as the subject of يَفْصِلُ)","p":{"وَ":["and"],"ٱللَّهُ":["Allah"],"ُ":["(as the subject of يَفْصِلُ)"]}},"60:3:11":{"w":"بِمَا","m":"with/by what (connects to تَعْمَلُونَ - you do)","p":{"بِ":["with/by"],"مَا":["what"]}},"60:3:12":{"w":"تَعْمَلُونَ","m":"you all do/work (referring to multiple people being addressed)","p":{"تَ":["you all"],"عْمَلُ":["do/work"],"ونَ":["(referring to multiple people being addressed)"]}},"60:3:13":{"w":"بَصِيرٌ","m":"All-Seeing (describing Allah in this ayah)","p":{"بَصِير":["All-Seeing"],"ٌ":["(describing Allah in this ayah)"]}},"60:4:1":{"w":"قَدْ","m":"certainly/definitely","p":{"قَدْ":["certainly/definitely"]}},"60:4:2":{"w":"كَانَتْ","m":"she/it was (referring to أُسْوَةٌ - example)","p":{"كَانَ":["was"],"تْ":["she/it"]}},"60:4:3":{"w":"لَكُمْ","m":"for you all","p":{"لَ":["for"],"كُمْ":["you all"]}},"60:4:4":{"w":"أُسْوَةٌ","m":"a perfect example (that is being described by حَسَنَةٌ)","p":{"أُسْوَ":["perfect example"],"ةٌ":["a"]}},"60:4:5":{"w":"حَسَنَةٌ","m":"a good/beautiful example (describing أُسْوَةٌ)","p":{"حَسَنَ":["good/beautiful"],"ةٌ":["a"]}},"60:4:6":{"w":"فِىٓ","m":"in (connecting to إِبْرٰهِيمَ)","p":{"فِى":["in"],"ٓ":["(connecting to إِبْرٰهِيمَ)"]}},"60:4:7":{"w":"إِبْرٰهِيمَ","m":"Abraham (as the object of قَوْلَ - saying of)","p":{"إِبْرٰهِيمَ":["Abraham"],"َ":["(as the object of قَوْلَ - saying of)"]}},"60:4:8":{"w":"وَٱلَّذِينَ","m":"and those who","p":{"وَ":["and"],"ٱلَّذِينَ":["those who"]}},"60:4:9":{"w":"مَعَهُۥٓ","m":"with him (possessed by الذين)","p":{"مَعَ":["with"],"هُۥٓ":["him"]}},"60:4:10":{"w":"إِذْ","m":"when (connects to قَالُوا۟ - they said)","p":{"إِذْ":["when"]}},"60:4:11":{"w":"قَالُوا۟","m":"they said (to their people)","p":{"قَال":["said"],"ُو":["they"],"ا۟":["(to their people)"]}},"60:4:12":{"w":"لِقَوْمِهِمْ","m":"to their people (object of قَالُوا)","p":{"لِ":["to"],"قَوْمِ":["people"],"هِمْ":["their"]}},"60:4:13":{"w":"إِنَّا","m":"indeed we (emphasizes that it's us speaking)","p":{"إِنَّ":["indeed"],"ا":["we"]}},"60:4:14":{"w":"بُرَءٰٓؤُا۟","m":"they became free/clear","p":{"بُرَءٰٓ":["free/clear"],"ؤُا۟":["they became"]}},"60:4:15":{"w":"مِنكُمْ","m":"from you all","p":{"مِن":["from"],"كُمْ":["you all"]}},"60:4:16":{"w":"وَمِمَّا","m":"and from what (that تَعْبُدُونَ you worship)","p":{"وَ":["and"],"مِ":["from"],"مَّا":["what"]}},"60:4:17":{"w":"تَعْبُدُونَ","m":"you (all) worship","p":{"تَ":["you"],"عْبُدُ":["worship"],"ونَ":["(all)"]}},"60:4:18":{"w":"مِن","m":"from/away from","p":{"مِ":["from"],"ن":["away"]}},"60:4:19":{"w":"دُونِ","m":"besides/other than (of اللَّهِ)","p":{"دُون":["besides/other than"],"ِ":["of"]}},"60:4:20":{"w":"ٱللَّهِ","m":"Allah (the one true God)","p":{"ٱل":["the"],"لَّه":["Allah","(the one true God)"],"ِ":[]}},"60:4:21":{"w":"كَفَرْنَا","m":"we rejected/denied (subject of بَدَا)","p":{"كَفَرْ":["rejected/denied"],"نَا":["we"]}},"60:4:22":{"w":"بِكُمْ","m":"in/with/by you all","p":{"بِ":["in/with/by"],"كُمْ":["you all"]}},"60:4:23":{"w":"وَبَدَا","m":"and it became apparent","p":{"وَ":["and"],"بَدَا":["it became apparent"]}},"60:4:24":{"w":"بَيْنَنَا","m":"between us (showing one side of the enmity and hatred)","p":{"بَيْنَ":["between"],"نَا":["us"]}},"60:4:25":{"w":"وَبَيْنَكُمُ","m":"and between you all","p":{"وَ":["and"],"بَيْنَ":["between"],"كُمُ":["you all"]}},"60:4:26":{"w":"ٱلْعَدٰوَةُ","m":"the hostility (doer)","p":{"ٱلْ":["the"],"عَدٰوَ":["hostility"],"ةُ":["(doer)"]}},"60:4:27":{"w":"وَٱلْبَغْضَآءُ","m":"and the intense hatred (subject of بَدَا)","p":{"وَ":["and"],"ٱلْ":["the"],"بَغْضَآءُ":["intense hatred"]}},"60:4:28":{"w":"أَبَدًا","m":"forever","p":{"أَبَد":["forever"],"ًا":["(accusative)"]}},"60:4:29":{"w":"حَتَّىٰ","m":"until (connects to تُؤْمِنُوا۟)","p":{"حَتَّىٰ":["until"]}},"60:4:30":{"w":"تُؤْمِنُوا۟","m":"you (all) believe (حَتَّىٰ until)","p":{"تُ":["you"],"ؤْمِن":["believe"],"ُوا۟":["(all)"]}},"60:4:31":{"w":"بِٱللَّهِ","m":"by/with Allah (connected to تُؤْمِنُوا - you believe)","p":{"بِ":["by/with"],"ٱللَّهِ":["Allah"]}},"60:4:32":{"w":"وَحْدَهُۥٓ","m":"Him alone (object of 'you believe' تُؤْمِنُوا)","p":{"وَحْدَ":["alone"],"هُۥٓ":["Him"]}},"60:4:33":{"w":"إِلَّا","m":"except (for قَوْلَ - the statement)","p":{"إِ":["except"],"لَّا":["(emphasizes the exception)"]}},"60:4:34":{"w":"قَوْلَ","m":"saying/speech (of إِبْرٰهِيمَ)","p":{"قَوْلَ":["saying/speech"]}},"60:4:35":{"w":"إِبْرٰهِيمَ","m":"Abraham (as the object being referred to)","p":{"إِبْرٰهِيمَ":["Abraham"],"َ":["(as the object being referred to)"]}},"60:4:36":{"w":"لِأَبِيهِ","m":"to his father","p":{"لِ":["to"],"أَبِي":["father"],"هِ":["his"]}},"60:4:37":{"w":"لَأَسْتَغْفِرَنَّ","m":"I will definitely seek forgiveness","p":{"لَ":["definitely"],"أَ":["I will"],"سْتَغْفِرَ":["seek forgiveness"],"نَّ":["definitely"]}},"60:4:38":{"w":"لَكَ","m":"for you/to you (object of أَمْلِكُ)","p":{"لَ":["for/to"],"كَ":["you"]}},"60:4:39":{"w":"وَمَآ","m":"and not (أَمْلِكُ)","p":{"وَ":["and"],"مَآ":["not"]}},"60:4:40":{"w":"أَمْلِكُ","m":"I possess/control (for اللَّهِ)","p":{"أَ":["I"],"مْلِكُ":["possess/control"]}},"60:4:41":{"w":"لَكَ","m":"for you (male) (object of أَسْتَغْفِرَنَّ)","p":{"لَ":["for"],"كَ":["you (male)"]}},"60:4:42":{"w":"مِنَ","m":"from (preposition, connected to اللَّهِ)","p":{"مِنَ":["from"]}},"60:4:43":{"w":"ٱللَّهِ","m":"Allah (the one true God)","p":{"ٱل":["the"],"لَّه":["Allah","(the one true God)"],"ِ":[]}},"60:4:44":{"w":"مِن","m":"from (showing separation)","p":{"مِ":["from"],"ن":["separation"]}},"60:4:45":{"w":"شَىْءٍ","m":"any thing (being acted upon)","p":{"شَىْء":["thing"],"ٍ":["any","(being acted upon)"]}},"60:4:46":{"w":"رَبَّنَا","m":"Our Master who nurtures and cares for us! (being called out to)","p":{"رَبَّ":["Master who nurtures and cares for"],"نَا":["Our","(being called out to)"]}},"60:4:48":{"w":"تَوَكَّلْنَا","m":"we put our trust (in عَلَيْكَ - in You)","p":{"تَ":["we"],"وَكَّلْ":["put trust"],"نَا":["we"]}},"60:4:49":{"w":"وَإِلَيْكَ","m":"and to you (connected to تَوَكَّلْنَا - we put our trust)","p":{"وَ":["and"],"إِلَيْ":["to"],"كَ":["you"]}},"60:4:50":{"w":"أَنَبْنَا","m":"we turned back (in repentance)","p":{"أَ":["turned back"],"نَبْ":["(in repentance)"],"نَا":["we"]}},"60:4:51":{"w":"وَإِلَيْكَ","m":"and to you (connected to تَوَكَّلْنَا - we relied upon)","p":{"وَ":["and"],"إِلَيْ":["to"],"كَ":["you"]}},"60:4:52":{"w":"ٱلْمَصِيرُ","m":"the final destination (in إِلَيْكَ ٱلْمَصِيرُ - to You is the final return)","p":{"ٱلْ":["the"],"مَ":["final"],"صِيرُ":["destination"]}},"60:5:1":{"w":"رَبَّنَا","m":"our Lord! (O our Lord!)","p":{"رَبَّ":["Lord"],"نَا":["our"],"ا":["!"]}},"60:5:2":{"w":"لَا","m":"no/not (negates تَجْعَلْنَا)","p":{"لَا":["no/not"]}},"60:5:3":{"w":"تَجْعَلْنَا","m":"make us (negative command after لَا)","p":{"تَ":["make"],"جْعَلْ":["make"],"نَا":["us"]}},"60:5:4":{"w":"فِتْنَةً","m":"a trial/test (object of تَجْعَلْنَا)","p":{"فِتْنَة":["trial/test"],"ً":["a"]}},"60:5:5":{"w":"لِّلَّذِينَ","m":"for those who (emphasized)","p":{"لِّ":["for"],"لَّذِينَ":["those who"],"ّ":["emphasized"]}},"60:5:6":{"w":"كَفَرُوا۟","m":"they rejected/denied (those who)","p":{"كَفَر":["rejected/denied"],"ُوا":["they"]}},"60:5:7":{"w":"وَٱغْفِرْ","m":"and forgive! (connected to لَا تَجْعَلْنَا - do not make us)","p":{"وَ":["and"],"ٱغْفِرْ":["forgive!"]}},"60:5:8":{"w":"لَنَا","m":"for us","p":{"لَ":["for"],"نَا":["us"]}},"60:5:9":{"w":"رَبَّنَا","m":"our Lord","p":{"رَبَّ":["Lord"],"نَا":["our"]}},"60:5:10":{"w":"إِنَّكَ","m":"indeed you","p":{"إِنَّ":["indeed"],"كَ":["you"]}},"60:5:11":{"w":"أَنتَ","m":"you","p":{"أَن":["you"],"تَ":["(masculine singular)"]}},"60:5:12":{"w":"ٱلْعَزِيزُ","m":"The Mighty One (a name of Allah)","p":{"ٱلْ":["The"],"عَزِي":["Mighty"],"زُ":["One"]}},"60:5:13":{"w":"ٱلْحَكِيمُ","m":"The All-Wise (Divine attribute of Allah)","p":{"ٱلْ":["The"],"حَكِيمُ":["All-Wise (Divine attribute of Allah)"]}},"60:6:1":{"w":"لَقَدْ","m":"indeed, certainly","p":{"لَ":["indeed"],"قَدْ":["certainly"]}},"60:6:2":{"w":"كَانَ","m":"he was","p":{"كَا":["was"],"نَ":["he"]}},"60:6:3":{"w":"لَكُمْ","m":"for you all","p":{"لَ":["for"],"كُمْ":["you all"]}},"60:6:4":{"w":"فِيهِمْ","m":"in them","p":{"فِي":["in"],"هِمْ":["them"]}},"60:6:5":{"w":"أُسْوَةٌ","m":"an example to follow (subject of كَانَ)","p":{"أُسْوَة":["an example to follow"],"ٌ":["(subject of كَانَ)"]}},"60:6:6":{"w":"حَسَنَةٌ","m":"a good/beautiful thing (feminine)","p":{"حَسَن":["good/beautiful"],"ة":["thing","feminine"],"ٌ":["a"]}},"60:6:7":{"w":"لِّمَن","m":"for whoever (with emphasis)","p":{"لِّ":["for"],"مَن":["whoever"],"ّ":["(with emphasis)"]}},"60:6:8":{"w":"كَانَ","m":"he was/existed","p":{"كَا":["was/existed"],"نَ":["he"]}},"60:6:10":{"w":"ٱللَّهَ","m":"Allah (as the object being referred to)","p":{"ٱللَّه":["Allah"],"َ":["(as the object being referred to)"]}},"60:6:11":{"w":"وَٱلْيَوْمَ","m":"and the day (object of يَرْجُوا - hopes for)","p":{"وَ":["and"],"ٱلْ":["the"],"يَوْمَ":["day"]}},"60:6:12":{"w":"ٱلْءَاخِرَ","m":"the last (one) (object of يَرْجُوا - hopes for)","p":{"ٱلْ":["the"],"ءَاخِرَ":["last (one)"]}},"60:6:13":{"w":"وَمَن","m":"and whoever (subject of يَتَوَلَّ)","p":{"وَ":["and"],"مَن":["whoever"]}},"60:6:14":{"w":"يَتَوَلَّ","m":"he turns away (in response to وَمَن - whoever)","p":{"يَ":["he"],"تَوَلَّ":["turns away"]}},"60:6:15":{"w":"فَإِنَّ","m":"then indeed (connects to يَتَوَلَّ - turns away)","p":{"فَ":["then"],"إِنَّ":["indeed"]}},"60:6:16":{"w":"ٱللَّهَ","m":"Allah (as the object being hoped for in يَرْجُوا۟)","p":{"ٱل":["the"],"لَّهَ":["Allah"],"َ":["(as the object being hoped for in يَرْجُوا۟)"]}},"60:6:17":{"w":"هُوَ","m":"He (referring to Allah)","p":{"هُ":["He"],"وَ":["(emphasis)"]}},"60:6:18":{"w":"ٱلْغَنِىُّ","m":"the Self-Sufficient (a name/attribute of Allah)","p":{"ٱلْ":["the"],"غَنِىُّ":["Self-Sufficient (a name/attribute of Allah)"]}},"60:6:19":{"w":"ٱلْحَمِيدُ","m":"The One who is constantly praised (a name/attribute of Allah)","p":{"ٱلْ":["The"],"حَمِيدُ":["One who is constantly praised (a name/attribute of Allah)"]}},"60:7:1":{"w":"عَسَى","m":"perhaps/it may be","p":{"عَسَى":["perhaps/it may be"]}},"60:7:2":{"w":"ٱللَّهُ","m":"Allah (the one true God)","p":{"ٱل":["the"],"لَّه":["Allah","(the one true God)"],"ُ":[]}},"60:7:3":{"w":"أَن","m":"that (connects 'perhaps' with 'He makes')","p":{"أَ":["that"],"ن":["(connector)"]}},"60:7:4":{"w":"يَجْعَلَ","m":"that he makes/puts/sets (after أَن)","p":{"يَ":["that he"],"جْعَلَ":["makes/puts/sets"]}},"60:7:5":{"w":"بَيْنَكُمْ","m":"between you all","p":{"بَيْنَ":["between"],"كُمْ":["you all"]}},"60:7:6":{"w":"وَبَيْنَ","m":"and between (connects to عَادَيْتُم - you showed enmity)","p":{"وَ":["and"],"بَيْنَ":["between"]}},"60:7:7":{"w":"ٱلَّذِينَ","m":"those who","p":{"ٱلَّذِي":["those who"],"نَ":["plural form"]}},"60:7:8":{"w":"عَادَيْتُ","m":"I showed hostility towards","p":{"عَادَيْ":["showed hostility"],"تُ":["I"]}},"60:7:9":{"w":"مِّنْهُم","m":"from them","p":{"مِّنْ":["from"],"هُم":["them"]}},"60:7:11":{"w":"وَٱللَّهُ","m":"and Allah (as the subject)","p":{"وَ":["and"],"ٱللَّه":["Allah"],"ُ":["as the subject"]}},"60:7:12":{"w":"قَدِيرٌ","m":"powerful (describes اللَّهُ)","p":{"قَدِير":["powerful"],"ٌ":["(describes اللَّهُ)"]}},"60:7:13":{"w":"وَٱللَّهُ","m":"and Allah (as the subject of قَدِيرٌ)","p":{"وَ":["and"],"ٱللَّهُ":["Allah"],"ُ":["(as the subject of قَدِيرٌ)"]}},"60:7:14":{"w":"غَفُورٌ","m":"Most Forgiving (as a name/attribute of اللَّهُ)","p":{"غَفُور":["Most Forgiving"],"ٌ":["(as a name/attribute of اللَّهُ)"]}},"60:7:15":{"w":"رَّحِيمٌ","m":"The Extremely Merciful One (a name/attribute of اللَّهُ)","p":{"رَّحِي":["Extremely Merciful"],"مٌ":["One"],"رَّ":["The"]}},"60:8:1":{"w":"لَّا","m":"not/do not (connected to يَنْهَىٰكُمُ - forbids you)","p":{"لَّا":["not/do not"]}},"60:8:2":{"w":"يَنْهَىٰكُمُ","m":"he stops/prevents you all","p":{"يَ":["he"],"نْهَىٰ":["stops/prevents"],"كُمُ":["you all"]}},"60:8:3":{"w":"إِلَهُ","m":"deity, god (in nominative case)","p":{"إِلَه":["deity, god"],"ُ":["(in nominative case)"]}},"60:8:4":{"w":"عَنِ","m":"from/away from (connects to ٱلَّذِينَ)","p":{"عَن":["from/away from"],"ِ":["(connects to ٱلَّذِينَ)"]}},"60:8:5":{"w":"ٱلَّذِينَ","m":"those who (plural)","p":{"ٱلَّذِي":["those who"],"نَ":["(plural)"]}},"60:8:6":{"w":"لَمْ","m":"did not (negates يُقٰتِلُوكُمْ)","p":{"لَ":["did"],"مْ":["not"]}},"60:8:7":{"w":"يُقَاتِلُوكُمْ","m":"they fight against you all","p":{"يُ":["they"],"قَاتِلُ":["fight against"],"و":["they"],"كُمْ":["you all"]}},"60:8:8":{"w":"فِي","m":"in (the religion)","p":{"فِ":["in"],"ي":["(connects to next word)"]}},"60:8:9":{"w":"ٱلدِّينِ","m":"of the religion","p":{"ٱل":["the"],"دِّين":["religion"],"ِ":["of"]}},"60:8:10":{"w":"وَلَمْ","m":"and not","p":{"وَ":["and"],"لَمْ":["not"]}},"60:8:11":{"w":"يُخْرِجُوكُم","m":"they expel you all","p":{"يُ":["they"],"خْرِجُ":["expel"],"و":["they"],"كُم":["you all"]}},"60:8:12":{"w":"مِّن","m":"from (emphasized)","p":{"مِّن":["from (emphasized)"]}},"60:8:13":{"w":"دِيٰرِكُمْ","m":"your homes","p":{"دِيٰرِ":["homes"],"كُمْ":["your"]}},"60:8:14":{"w":"أَن","m":"that (connects to تَبَرُّوهُمْ - you be good to them)","p":{"أَ":["that"],"ن":["connects what follows"]}},"60:8:15":{"w":"تَبَرُّوهُمْ","m":"you all do good to them","p":{"تَ":["you all"],"بَرُّ":["do good"],"و":["to"],"هُمْ":["them"]}},"60:8:16":{"w":"وَتُقْسِطُوٓا۟","m":"and that you all act justly (to them)","p":{"وَ":["and"],"تُ":["you all"],"قْسِطُ":["act justly"],"وٓا۟":["(to them)"]}},"60:8:17":{"w":"إِلَيْهِمْ","m":"to them (receiving تَبَرُّوهُمْ وَتُقْسِطُوٓا۟)","p":{"إِلَيْ":["to"],"هِمْ":["them"]}},"60:8:18":{"w":"إِنَّ","m":"indeed/truly (emphasizes that اللَّهَ loves the just)","p":{"إِنَّ":["indeed/truly"]}},"60:8:19":{"w":"ٱللَّهَ","m":"Allah (as the object of يُحِبُّ - He loves)","p":{"ٱل":["the"],"لَّهَ":["Allah"],"َ":["(as the object of يُحِبُّ - He loves)"]}},"60:8:20":{"w":"يُحِبُّ","m":"he loves (subject is اللَّهَ - Allah)","p":{"يُ":["he"],"حِبُّ":["loves"]}},"60:8:21":{"w":"ٱلْمُقْسِطِينَ","m":"the ones who act with fairness (object of يُحِبُّ)","p":{"ٱلْ":["the"],"مُ":["ones who"],"قْسِطِ":["act with fairness"],"ينَ":["(object of يُحِبُّ)"]}},"60:9:1":{"w":"إِنَّمَا","m":"only/just/nothing but","p":{"إِنَّ":["only/just"],"مَا":["nothing but"]}},"60:9:2":{"w":"يَنْهَىٰكُمُ","m":"he prevents/stops you all","p":{"يَ":["he"],"نْهَىٰ":["prevents/stops"],"كُمُ":["you all"]}},"60:9:3":{"w":"ٱللَّهُ","m":"Allah (subject of يَنْهَىٰكُمُ)","p":{"ٱل":["the"],"لَّه":["Allah"],"ُ":["(subject of يَنْهَىٰكُمُ)"]}},"60:9:4":{"w":"عَنِ","m":"away from (connects to ٱلَّذِينَ)","p":{"عَن":["away from"],"ِ":["(connects to ٱلَّذِينَ)"]}},"60:9:5":{"w":"ٱلَّذِينَ","m":"those who (fought against you)","p":{"ٱلَّذِي":["those who"],"نَ":["(fought against you)"]}},"60:9:6":{"w":"قٰتَلُوكُمْ","m":"they fought against you all","p":{"قٰتَ":["fought against"],"لُو":["they"],"كُمْ":["you all"]}},"60:9:7":{"w":"فِي","m":"in/within (connects to الدِّينِ)","p":{"فِ":["in"],"ي":["within"]}},"60:9:8":{"w":"ٱلدِّينِ","m":"the religion (affected by فِى)","p":{"ٱل":["the"],"دِّينِ":["religion (affected by فِى)"]}},"60:9:9":{"w":"وَأَخْرَجُوكُم","m":"and they expelled you all","p":{"وَ":["and"],"أَخْرَجُو":["they expelled"],"كُم":["you all"]}},"60:9:10":{"w":"مِّن","m":"from (دِيٰرِكُمْ your homes)","p":{"مِّن":["from"]}},"60:9:11":{"w":"دِيٰرِكُمْ","m":"your homes/dwellings","p":{"دِيٰرِ":["homes/dwellings"],"كُمْ":["your"]}},"60:9:12":{"w":"وَظٰهَرُوا۟","m":"and they supported","p":{"وَ":["and"],"ظٰهَرُ":["supported"],"وا۟":["they"]}},"60:9:13":{"w":"عَلَىٰٓ","m":"upon/against (your expulsion)","p":{"عَلَىٰٓ":["upon/against"]}},"60:9:14":{"w":"إِخْرَاجِ","m":"your expulsion","p":{"إِخْرَاجِ":["expulsion"],"كُمْ":["your"]}},"60:9:15":{"w":"أَن","m":"that (connects to تَوَلَّوْهُمْ)","p":{"أَ":["that"],"ن":["connects ideas"]}},"60:9:16":{"w":"تَوَلَّوْهُمْ","m":"they took them as allies","p":{"تَوَلَّوْ":["they took as allies"],"هُمْ":["them"]}},"60:9:18":{"w":"يَتَوَلَّهُمْ","m":"he takes them as allies","p":{"يَ":["he"],"تَوَلَّ":["takes as allies"],"هُمْ":["them"]}},"60:9:19":{"w":"فَأُولٰٓئِكَ","m":"then those (far)","p":{"فَ":["then"],"أُولٰٓ":["those"],"ئِكَ":["(far)"]}},"60:9:20":{"w":"هُمُ","m":"they (subject of الظَّالِمُونَ)","p":{"هُمُ":["they"]}},"60:9:21":{"w":"ٱلظَّالِمُونَ","m":"the wrongdoers (predicate of هم)","p":{"ٱل":["the"],"ظَّالِم":["wrongdoers"],"ُونَ":["(predicate of هم)"]}},"60:10:1":{"w":"يٰٓأَيُّهَا","m":"O you","p":{"يٰٓأَيُّ":["O"],"هَا":["you"]}},"60:10:2":{"w":"ٱلَّذِينَ","m":"those who","p":{"ٱلَّ":["those"],"ذِينَ":["who"]}},"60:10:3":{"w":"ءَامَنُوٓا۟","m":"they believed","p":{"ءَامَن":["believed"],"ُوٓا۟":["they"]}},"60:10:4":{"w":"إِذَا","m":"when, whenever (future time)","p":{"إِذَا":["when, whenever (future time)"]}},"60:10:5":{"w":"جَآءَكُمُ","m":"he came to you all","p":{"جَآءَ":["he came"],"كُمُ":["to you all"]}},"60:10:6":{"w":"ٱلْمُؤْمِنٰتُ","m":"the believing women (who are coming as refugees)","p":{"ٱلْ":["the"],"مُؤْمِن":["believing"],"ٰتُ":["women"]}},"60:10:7":{"w":"مُهٰجِرٰتٍ","m":"women who left their homes (to seek safety)","p":{"مُ":["who"],"هٰجِر":["left their homes"],"ٰتٍ":["women","(to seek safety)"]}},"60:10:8":{"w":"فَٱمْتَحِنُوهُنَّ","m":"so test them (women)","p":{"فَ":["so"],"ٱمْتَحِنُو":["test"],"هُنَّ":["them (women)"]}},"60:10:9":{"w":"ٱلْإِلَهُ","m":"the deity, the god","p":{"ٱلْ":["the"],"إِلَهُ":["deity","god"]}},"60:10:10":{"w":"أَعْلَمُ","m":"more knowing (than اللَّهُ)","p":{"أَ":["more"],"عْلَمُ":["knowing"]}},"60:10:11":{"w":"بِإِيمٰنِهِنَّ","m":"with their (feminine) faith","p":{"بِ":["with"],"إِيمٰنِ":["faith"],"هِنَّ":["their (feminine)"]}},"60:10:12":{"w":"فَإِنْ","m":"then if (connects test to result)","p":{"فَ":["then"],"إِنْ":["if"]}},"60:10:13":{"w":"عَلِمْتُمُوهُنَّ","m":"you all knew them (feminine)","p":{"عَلِمْ":["knew"],"تُمُو":["you all"],"هُنَّ":["them (feminine)"]}},"60:10:14":{"w":"مُؤْمِنٰتٍ","m":"believing women (as the object being described)","p":{"مُؤْمِن":["believing"],"ٰتٍ":["women (as the object being described)"]}},"60:10:15":{"w":"فَلَا","m":"so/then not","p":{"فَ":["so/then"],"لَا":["not"]}},"60:10:16":{"w":"تَرْجِعُوهُنَّ","m":"you all return them (feminine)","p":{"تَ":["you all"],"رْجِعُ":["return"],"و":["you all"],"هُنَّ":["them (feminine)"]}},"60:10:17":{"w":"إِلَى","m":"to/towards (connects تَرْجِعُوهُنَّ with ٱلْكُفَّارِ)","p":{"إِ":["to"],"لَى":["towards"]}},"60:10:18":{"w":"الكفّارِ","m":"to/of the strong rejecters of truth","p":{"ال":["the"],"كفّار":["strong rejecters of truth"],"ِ":["to/of"]}},"60:10:19":{"w":"لَا","m":"no/not (negates تَرْجِعُوهُنَّ)","p":{"لَا":["no/not"]}},"60:10:20":{"w":"هُنَّ","m":"they (feminine plural)","p":{"هُ":["they"],"نَّ":["feminine plural"]}},"60:10:21":{"w":"حِلٌّ","m":"a permissible thing","p":{"حِل":["permissible"],"ٌّ":["a","thing"]}},"60:10:22":{"w":"لَّهُمْ","m":"for them (masculine plural)","p":{"لَّ":["for"],"هُمْ":["them (masculine plural)"]}},"60:10:23":{"w":"وَلَا","m":"and not (negates يَحِلُّونَ)","p":{"وَ":["and"],"لَا":["not"]}},"60:10:24":{"w":"هُمْ","m":"they/them (masculine plural) (object of حِلٌّ - lawful)","p":{"هُمْ":["they/them (masculine plural)"]}},"60:10:25":{"w":"يَحِلُّونَ","m":"they are allowed","p":{"يَ":["they"],"حِلُّ":["are allowed"],"ونَ":["they"]}},"60:10:26":{"w":"لَهُنَّ","m":"to/for them (feminine plural)","p":{"لَ":["to/for"],"هُ":["them"],"نَّ":["(feminine plural)"]}},"60:10:28":{"w":"مَّآ","m":"what/that which (emphasized and lengthened)","p":{"مَّ":["what/that which (emphasized)"],"آ":["(lengthened)"]}},"60:10:29":{"w":"أَنْفَقُوا۟","m":"they spent","p":{"أَ":["spent"],"نْفَقُ":["spent"],"وا۟":["they"]}},"60:10:30":{"w":"وَلَا","m":"and not","p":{"وَ":["and"],"لَا":["not"]}},"60:10:31":{"w":"جُنَاحَ","m":"sin, blame, fault","p":{"جُنَاحَ":["sin, blame, fault"]}},"60:10:32":{"w":"عَلَيْكُمْ","m":"upon you all","p":{"عَلَيْ":["upon"],"كُمْ":["you all"]}},"60:10:33":{"w":"أَن","m":"that (you marry them)","p":{"أَ":["that"],"ن":["connects to what follows"]}},"60:10:34":{"w":"تَنكِحُوهُنَّ","m":"you (all) marry them (feminine plural)","p":{"تَ":["you"],"نكِحُ":["marry"],"و":["(all)"],"هُنَّ":["them (feminine plural)"]}},"60:10:35":{"w":"إِذَآ","m":"when (connecting to ءَاتَيْتُمُوهُنَّ - you give them)","p":{"إِذَآ":["when"]}},"60:10:36":{"w":"ءَاتَيْتُمُوهُنَّ","m":"you all gave them (feminine)","p":{"ءَاتَيْ":["gave"],"تُمُو":["you all"],"هُنَّ":["them (feminine)"]}},"60:10:37":{"w":"أُجُورَهُنَّ","m":"their compensation (feminine plural)","p":{"أُجُورَ":["compensation"],"هُنَّ":["their (feminine plural)"]}},"60:10:38":{"w":"وَلَا","m":"and not (negates يَحِلُّونَ)","p":{"وَ":["and"],"لَا":["not"]}},"60:10:39":{"w":"تُمْسِكُوا۟","m":"you (all) grasp","p":{"تُ":["you"],"مْسِكُ":["grasp"],"وا۟":["(all)"]}},"60:10:40":{"w":"بِعِصَمِ","m":"by/with bonds (connected to تُمْسِكُوا)","p":{"بِ":["by/with"],"عِصَمِ":["bonds"]}},"60:10:41":{"w":"ٱلْكَوَافِرِ","m":"the disbelieving women (possessed by عِصَمِ)","p":{"ٱلْ":["the"],"كَوَافِرِ":["disbelieving women"]}},"60:10:42":{"w":"وَسْأَلُوا","m":"and they asked","p":{"وَ":["and"],"سْأَلُ":["asked"],"وا":["they"]}},"60:10:43":{"w":"مَآ","m":"what (that was spent)","p":{"مَآ":["what (that was spent)"]}},"60:10:44":{"w":"أَنْفَقْتُمْ","m":"you all spent","p":{"أَ":["spent"],"نْفَقْ":["spent"],"تُمْ":["you all"]}},"60:10:45":{"w":"وَلْيَسْـَٔلُوا۟","m":"and let them ask (what they spent)","p":{"وَ":["and"],"لْ":["let"],"يَسْـَٔلُوا":["them ask"]}},"60:10:46":{"w":"مَآ","m":"what (connects to أَنفَقُوا۟ - they spent)","p":{"مَآ":["what"]}},"60:10:47":{"w":"أَنفَقُوا","m":"they spent (referring to previous husbands in the ayah)","p":{"أَنفَق":["spent"],"وا":["they"]}},"60:10:48":{"w":"ذٰلِكُمْ","m":"that (addressing multiple people)","p":{"ذٰلِ":["that"],"كُمْ":["(addressing multiple people)"]}},"60:10:49":{"w":"حُكْمُ","m":"judgment/ruling (subject of اللَّهِ - belongs to Allah)","p":{"حُكْم":["judgment/ruling"],"ُ":["(subject of اللَّهِ - belongs to Allah)"]}},"60:10:50":{"w":"ٱللَّهِ","m":"of Allah (judgment of Allah)","p":{"ٱللَّه":["Allah"],"ِ":["of"]}},"60:10:51":{"w":"يَحْكُمُ","m":"he decides/rules (Allah's judgment)","p":{"يَ":["he"],"حْكُمُ":["decides/rules"]}},"60:10:52":{"w":"بَيْنَكُمْ","m":"between you all","p":{"بَيْنَ":["between"],"كُمْ":["you all"]}},"60:10:53":{"w":"وَٱللَّهُ","m":"And Allah (subject of يَحْكُمُ)","p":{"وَ":["And"],"ٱللَّهُ":["Allah"],"ُ":["(subject of يَحْكُمُ)"]}},"60:10:54":{"w":"عَلِيمٌ","m":"All-Knowing (as a permanent attribute of اللَّهُ)","p":{"عَلِي":["All-Knowing"],"مٌ":["(as a permanent attribute of اللَّهُ)"]}},"60:10:55":{"w":"حَكِيمٌ","m":"All-Wise (describing اللَّهُ)","p":{"حَكِي":["All-Wise"],"مٌ":["(describing اللَّهُ)"]}},"60:11:2":{"w":"فَاتَكُمْ","m":"it escaped you all (referring to something mentioned in أَزْوٰجِكُمْ)","p":{"فَات":["it escaped"],"كُمْ":["you all"]}},"60:11:3":{"w":"شَىْءٌ","m":"a thing (subject of فَاتَ - escapes/departs)","p":{"شَىْء":["thing"],"ٌ":["a"]}},"60:11:4":{"w":"مِّنْ","m":"from (of أَزْوٰجِكُمْ - your spouses)","p":{"مِّنْ":["from"]}},"60:11:5":{"w":"أَزْوٰجِكُمْ","m":"your (plural) spouses","p":{"أَزْوٰجِ":["spouses"],"كُمْ":["your (plural)"]}},"60:11:6":{"w":"إِلَى","m":"to/towards (the disbelievers)","p":{"إِ":["to"],"لَى":["towards"]}},"60:11:7":{"w":"ٱلْكُفَّارِ","m":"of the intense deniers of truth","p":{"ٱلْ":["the"],"كُفَّار":["intense deniers of truth"],"ِ":["of"]}},"60:11:8":{"w":"فَعَاقَبْتُمْ","m":"and then you all punished (as a consequence of what was mentioned before)","p":{"فَ":["and then"],"عَاقَبْ":["punished"],"تُمْ":["you all"]}},"60:11:9":{"w":"فَأَتُوا","m":"so you (all) come/bring","p":{"فَ":["so"],"أتُ":["come/bring"],"وا":["you (all)"]}},"60:11:10":{"w":"ٱلَّذِينَ","m":"those who (plural)","p":{"ٱلَّذِي":["those who"],"نَ":["(plural)"]}},"60:11:11":{"w":"ذَهَبَتْ","m":"she went (referring to أَزْوٰجُهُم - their spouses)","p":{"ذَهَبَ":["went"],"تْ":["she"]}},"60:11:12":{"w":"أَزْوٰجُهُم","m":"their spouses (referring to the wives of believers who fled to the disbelievers)","p":{"أَزْوٰجُ":["spouses"],"هُم":["their"]}},"60:11:13":{"w":"مِّثْلَ","m":"like/similar to (of ما)","p":{"مِّثْلَ":["like/similar to"]}},"60:11:14":{"w":"مَآ","m":"what (referring to what was spent)","p":{"مَآ":["what"]}},"60:11:15":{"w":"أَنفَقُوا۟","m":"they spent","p":{"أَ":["they"],"نفَق":["spent"],"ُوا۟":["they"]}},"60:11:16":{"w":"وَٱتَّقُوا۟","m":"and you all protect yourselves (from ٱللَّهَ - Allah)","p":{"وَ":["and"],"ٱتَّقُ":["protect yourselves"],"وا۟":["you all"]}},"60:11:17":{"w":"ٱللَّهَ","m":"Allah (as the object being feared/revered)","p":{"ٱللَّه":["Allah"],"َ":["(as the object being feared/revered)"]}},"60:11:18":{"w":"ٱلَّذِىٓ","m":"the one who/which (connects to أَنتُم)","p":{"ٱلَّ":["the"],"ذِ":["one"],"ىٓ":["who/which"]}},"60:11:19":{"w":"أَنتُم","m":"you all (when speaking to a group)","p":{"أَنت":["you"],"ُم":["all (when speaking to a group)"]}},"60:11:20":{"w":"بِهِۦ","m":"with/by/in him/it","p":{"بِ":["with/by/in"],"هِۦ":["him/it"]}},"60:11:21":{"w":"مُؤْمِنُونَ","m":"believers (subject of أَنتُم)","p":{"مُؤْمِن":["believers"],"ُونَ":["(subject of أَنتُم)"]}},"60:12:1":{"w":"يٰأيُّهَا","m":"O (you) who","p":{"يٰ":["O"],"أيُّ":["who"],"هَا":["(you)"]}},"60:12:2":{"w":"اَلنَّبِيُّ","m":"the prophet (as subject)","p":{"اَل":["the"],"نَّبِيُّ":["prophet"],"ُ":["(as subject)"]}},"60:12:3":{"w":"إِذَا","m":"when, whenever (introduces condition for جَآءَكَ - comes to you)","p":{"إِذَا":["when, whenever"]}},"60:12:4":{"w":"جَآءَكَ","m":"he came to you (O Prophet)","p":{"جَآءَ":["he came"],"كَ":["to you (O Prophet)"]}},"60:12:5":{"w":"ٱلْمُؤْمِنٰتُ","m":"the believing women (who are coming to يُبَايِعْنَكَ - pledge allegiance to you)","p":{"ٱلْ":["the"],"مُؤْمِن":["believing"],"ٰتُ":["women"]}},"60:12:6":{"w":"يُبَايِعْنَكَ","m":"they (women) make a mutual pledge to you (addressing the Prophet ﷺ)","p":{"يُ":["they (women)"],"بَايِعْ":["make a mutual pledge"],"نَ":["they (women)"],"كَ":["to you"]}},"60:12:7":{"w":"عَلَىٰٓ","m":"on/upon","p":{"عَلَىٰٓ":["on/upon"]}},"60:12:8":{"w":"أَن","m":"that (connects to لَّا يُشْرِكْنَ - they do not associate)","p":{"أَن":["that"]}},"60:12:9":{"w":"لَّا","m":"absolutely not/definitely don't","p":{"لَّا":["absolutely not/definitely don't"]}},"60:12:10":{"w":"يُشْرِكْنَ","m":"they (fem pl) associate/share","p":{"يُ":["they"],"شْرِكْ":["associate/share"],"نَ":["fem pl"]}},"60:12:11":{"w":"بِٱللَّهِ","m":"by/with Allah","p":{"بِ":["by/with"],"ٱللَّهِ":["Allah"]}},"60:12:12":{"w":"شَيْـًٔا","m":"anything (that is being associated with Allah)","p":{"شَيْ":["anything"],"ـًٔا":["(that is being associated with Allah)"]}},"60:12:13":{"w":"وَلَا","m":"and not","p":{"وَ":["and"],"لَا":["not"]}},"60:12:14":{"w":"يَسْرِقْنَ","m":"they (women) steal (part of a pledge to not steal)","p":{"يَ":["steal"],"سْرِقْ":["steal"],"نَ":["they (women)"]}},"60:12:15":{"w":"وَلَا","m":"and not (negates يَسْرِقْنَ)","p":{"وَ":["and"],"لَا":["not"]}},"60:12:16":{"w":"يَزْنِينَ","m":"they (women) do this forbidden act","p":{"يَ":["do"],"زْنِي":["this forbidden act"],"نَ":["they (women)"]}},"60:12:17":{"w":"وَلَا","m":"and not","p":{"وَ":["and"],"لَا":["not"]}},"60:12:18":{"w":"يَقْتُلْنَ","m":"they (women) kill","p":{"يَ":["they"],"قْتُلْ":["kill"],"نَ":["(women)"]}},"60:12:19":{"w":"أَوْلٰدَهُنَّ","m":"their (feminine plural) children","p":{"أَوْلٰدَ":["children"],"هُنَّ":["their (feminine plural)"]}},"60:12:20":{"w":"وَلَا","m":"and not (negates يَأْتِينَ - they bring)","p":{"وَ":["and"],"لَا":["not"]}},"60:12:21":{"w":"يَأْتِينَ","m":"they (feminine plural) come/arrive","p":{"يَ":["come/arrive"],"أْتِ":["come/arrive"],"نَ":["they (feminine plural)"]}},"60:12:22":{"w":"بِبُهْتٰنٍ","m":"with a serious false accusation","p":{"بِ":["with"],"بُهْتٰ":["serious false accusation"],"نٍ":["a"]}},"60:12:23":{"w":"يَفْتَرِينَهُۥ","m":"they (feminine) fabricate it","p":{"يَ":["they (feminine)"],"فْتَرِي":["fabricate"],"نَ":["they (feminine)"],"هُۥ":["it"]}},"60:12:24":{"w":"بَيْنَ","m":"between","p":{"بَيْنَ":["between"]}},"60:12:25":{"w":"أَيْدِيهِنَّ","m":"their (feminine plural) hands","p":{"أَيْدِي":["hands"],"هِنَّ":["their (feminine plural)"]}},"60:12:26":{"w":"وَأَرْجُلِهِنَّ","m":"and their feet (feminine plural)","p":{"وَ":["and"],"أَرْجُلِ":["feet"],"هِنَّ":["their (feminine plural)"]}},"60:12:27":{"w":"وَلَا","m":"and not (negates يَعْصِينَكَ)","p":{"وَ":["and"],"لَا":["not"]}},"60:12:28":{"w":"يَعْصِينَكَ","m":"they (women) disobey you","p":{"يَ":["they (women)"],"عْصِي":["disobey"],"نَ":["they (women)"],"كَ":["you"]}},"60:12:29":{"w":"فِى","m":"in (location for مَعْرُوفٍ)","p":{"فِى":["in"]}},"60:12:30":{"w":"مَعْرُوفٍ","m":"any good/acceptable deed (in matters of فِى)","p":{"مَ":["any"],"عْرُوف":["good/acceptable deed"],"ٍ":["(in matters of فِى)"]}},"60:12:31":{"w":"فَبَايِعْهُنَّ","m":"so make a mutual pledge with them (feminine plural)","p":{"فَ":["so"],"بَايِعْ":["make a mutual pledge with"],"هُنَّ":["them (feminine plural)"]}},"60:12:32":{"w":"وَٱسْتَغْفِرْ","m":"and seek forgiveness! (command to Prophet ﷺ)","p":{"وَ":["and"],"ٱسْتَغْفِرْ":["seek forgiveness! (command to Prophet ﷺ)"]}},"60:12:33":{"w":"لَهُنَّ","m":"for them (feminine plural, referring to the believing women)","p":{"لَ":["for"],"هُنَّ":["them (feminine plural, referring to the believing women)"]}},"60:12:34":{"w":"ٱللَّهَ","m":"Allah (as the object being described as غَفُورٌ رَّحِيمٌ - Most Forgiving, Most Merciful)","p":{"ٱل":["the"],"لَّهَ":["Allah"],"َ":["(as the object being described as غَفُورٌ رَّحِيمٌ - Most Forgiving, Most Merciful)"]}},"60:12:35":{"w":"إِنَّ","m":"indeed/truly (emphasizes what follows)","p":{"إِ":["indeed"],"نَّ":["truly/certainly"]}},"60:12:36":{"w":"ٱللَّهَ","m":"Allah (the One True God who is the object of يَسْتَغْفِرْ/seeking forgiveness)","p":{"ٱل":["the"],"لَّهَ":["Allah (the One True God who is the object of يَسْتَغْفِرْ/seeking forgiveness)"]}},"60:12:37":{"w":"غَفُورٌ","m":"Most Forgiving (describing اللَّهَ)","p":{"غَفُور":["Most Forgiving"],"ٌ":["(describing اللَّهَ)"]}},"60:12:38":{"w":"رَّحِيمٌ","m":"Most Merciful (describing Allah, paired with غَفُورٌ/Most Forgiving)","p":{"رَّحِيم":["Most Merciful"],"ٌ":["(describing Allah, paired with غَفُورٌ/Most Forgiving)"]}},"60:13:1":{"w":"يٰٓأَيُّهَا","m":"O you who... (addressing a group)","p":{"يٰٓ":["O"],"أَيُّ":["who"],"هَا":["you... (addressing a group)"]}},"60:13:2":{"w":"ٱلَّذِينَ","m":"those who (subject of ءَامَنُوا۟)","p":{"ٱلَّذِي":["those who"],"نَ":["(subject of ءَامَنُوا۟)"]}},"60:13:3":{"w":"ءَامَنُوا۟","m":"they believed (referring to the believers being addressed)","p":{"ءَامَن":["believed"],"ُو":["they"],"ا۟":["(referring to the believers being addressed)"]}},"60:13:4":{"w":"لَا","m":"do not (negating تَتَوَلَّوْا۟)","p":{"لَ":["do"],"ا":["not"]}},"60:13:5":{"w":"تَتَوَلَّوْا۟","m":"you all turn away (from قَوْمًا)","p":{"تَ":["you all"],"تَوَلَّ":["turn away"],"وْا۟":["you all"]}},"60:13:6":{"w":"قَوْمًا","m":"a people (who are being warned not to be taken as allies)","p":{"قَوْم":["people"],"ًا":["a"]}},"60:13:7":{"w":"غَضِبَ","m":"he became angry","p":{"غَضِبَ":["he became angry"]}},"60:13:8":{"w":"ٱللَّهُ","m":"Allah (subject of غَضِبَ - became angry)","p":{"ٱل":["the"],"لَّه":["Allah"],"ُ":["subject of غَضِبَ - became angry"]}},"60:13:9":{"w":"عَلَيْهِمْ","m":"upon them","p":{"عَلَيْ":["upon"],"هِمْ":["them"]}},"60:13:10":{"w":"قَدْ","m":"indeed/certainly","p":{"قَدْ":["indeed/certainly"]}},"60:13:11":{"w":"يَئِسُوا","m":"they lost hope","p":{"يَئِس":["lost hope"],"وا":["they"]}},"60:13:12":{"w":"مِنَ","m":"from (connected to ٱلْءَاخِرَةِ)","p":{"مِنَ":["from"]}},"60:13:13":{"w":"ٱلْءَاخِرَةِ","m":"of the afterlife","p":{"ٱلْ":["the"],"ءَاخِرَةِ":["afterlife"],"ِ":["of"]}},"60:13:14":{"w":"كَمَا","m":"just like, similar to","p":{"كَ":["like"],"مَا":["just","similar to"]}},"60:13:15":{"w":"يَئِسَ","m":"he lost hope (from ٱلْءَاخِرَةِ - the Hereafter)","p":{"يَ":["he"],"ئِسَ":["lost hope"]}},"60:13:16":{"w":"ٱلْكُفَّارُ","m":"the disbelievers","p":{"ٱلْ":["the"],"كُفَّارُ":["disbelievers"]}},"60:13:17":{"w":"مِنْ","m":"from (connecting يَئِسَ with أَصْحٰبِ)","p":{"مِ":["from"],"نْ":["connection marker"]}},"60:13:18":{"w":"أَصْحٰبِ","m":"companions (of القُبُورِ - the graves)","p":{"أَصْحٰبِ":["companions"],"ِ":["of"]}},"60:13:19":{"w":"الْقُبُورِ","m":"of the graves (possessed by أَصْحٰبِ/dwellers)","p":{"ال":["the"],"قُبُور":["graves"],"ِ":["of"]}}}