{"83:1:1":{"w":"وَيْلٌ","m":"woe/destruction (subject of the sentence)","p":{"وَيْل":["woe/destruction"],"ٌ":["(subject of the sentence)"]}},"83:1:2":{"w":"ٱلْمُطَفِّفِين","m":"the ones who cheat in measurement","p":{"ٱلْ":["the"],"مُ":["ones who"],"طَفِّفِ":["cheat in measurement"],"ين":["ones who"]}},"83:2:1":{"w":"ٱلَّذِينَ","m":"those who (referring to the cheaters in measuring mentioned later)","p":{"ٱلَّذِي":["those who"],"نَ":["(referring to the cheaters in measuring mentioned later)"]}},"83:2:2":{"w":"إِذَا","m":"when","p":{"إِذَا":["when"]}},"83:2:3":{"w":"ٱكْتَالُوا۟","m":"they took measurements for themselves (from others)","p":{"ٱ":["they"],"كْتَالُ":["took measurements for themselves"],"وا۟":["they"]}},"83:2:4":{"w":"عَلَى","m":"against (the people)","p":{"عَلَ":["against"],"ى":["extension of meaning"]}},"83:2:5":{"w":"ٱلنَّاسِ","m":"of/from the people","p":{"ٱل":["the"],"نَّاس":["people"],"ِ":["of/from"]}},"83:2:6":{"w":"يَسْتَوْفُونَ","m":"they demand in full","p":{"يَ":["they"],"سْتَوْفُ":["demand in full"],"ونَ":["they"]}},"83:3:1":{"w":"وَإِذَا","m":"and when","p":{"وَ":["and"],"إِذَا":["when"]}},"83:3:2":{"w":"كَالُوهُمْ","m":"they measured out for them","p":{"كَا":["measured"],"لُو":["they"],"هُمْ":["for them"]}},"83:3:3":{"w":"أَو","m":"or (connecting measuring with weighing)","p":{"أَ":["introduces choice"],"و":["or"]}},"83:3:4":{"w":"وَّزَنُوهُمْ","m":"and they weighed them","p":{"وَّ":["and"],"زَنُ":["weighed"],"و":["they"],"هُمْ":["them"]}},"83:3:5":{"w":"يُخْسِرُونَ","m":"they make (others) lose (when measuring for them)","p":{"يُ":["they"],"خْسِر":["make lose"],"ُونَ":["(others)"]}},"83:4:1":{"w":"أَلَا","m":"Indeed! (introducing يَظُنُّ - they think)","p":{"أَ":["Indeed"],"لَا":["!"]}},"83:4:2":{"w":"يَظُنُّ","m":"he thinks/is thinking (about being resurrected)","p":{"يَ":["he"],"ظُنُّ":["thinks/is thinking (about being resurrected)"]}},"83:4:3":{"w":"أُو۟لٰٓئِكَ","m":"those people over there (subject of يَظُنُّ)","p":{"أُو۟لٰٓئِكَ":["those people over there"]}},"83:4:4":{"w":"أَنَّهُم","m":"that they (the ones being thought about)","p":{"أَنَّ":["that"],"هُم":["they (the ones being thought about)"]}},"83:4:5":{"w":"مَّبْعُوثُون","m":"those who are DEFINITELY sent forth/resurrected","p":{"مَّ":["DEFINITELY"],"بْعُوثُ":["sent forth/resurrected"],"ون":["those who are"]}},"83:5:1":{"w":"لِيَوْمٍ","m":"for a day (connected to عَظِيمٍ - great)","p":{"لِ":["for"],"يَوْ":["day"],"مٍ":["a"]}},"83:5:2":{"w":"عَظِيمٍ","m":"mighty/magnificent (describing يَوْمٍ, in a possessive/connected state)","p":{"عَظِيم":["mighty/magnificent"],"ٍ":["(describing يَوْمٍ, in a possessive/connected state)"]}},"83:6:1":{"w":"يَوْمَ","m":"on the Day (when people stand)","p":{"يَوْمَ":["Day"],"َ":["on the"]}},"83:6:3":{"w":"ٱلنَّاسُ","m":"the people (subject of يَقُومُ - stands/rises)","p":{"ٱل":["the"],"نَّاسُ":["people"],"ُ":["subject of يَقُومُ - stands/rises"]}},"83:6:4":{"w":"لِرَبِّ","m":"for/to the master/lord (being described by الْعٰلَمِينَ)","p":{"لِ":["for/to"],"رَبِّ":["master/lord"],"ِ":["the"]}},"83:6:5":{"w":"ٱلْعٰلَمِينَ","m":"the worlds (possessed by رَبِّ)","p":{"ٱلْ":["the"],"عٰلَمِ":["worlds"],"ينَ":["(possessed by رَبِّ)"]}},"83:7:1":{"w":"كَلَّآ","m":"No indeed! (strongly rejecting what was mentioned before)","p":{"كَلَّآ":["No indeed! (strongly rejecting what was mentioned before)"]}},"83:7:2":{"w":"إِنَّ","m":"indeed/truly (emphasizes كِتٰبَ ٱلْفُجَّارِ)","p":{"إِنَّ":["indeed/truly"]}},"83:7:3":{"w":"كِتٰبَ","m":"book (object of إِنَّ)","p":{"كِتٰبَ":["book"]}},"83:7:4":{"w":"ٱلْفُجَّارِ","m":"of the wicked people (possessed by كِتٰبَ)","p":{"ٱلْ":["the"],"فُجَّارِ":["wicked people"],"ِ":["of"]}},"83:7:5":{"w":"لَفِى","m":"surely in/within","p":{"لَ":["surely"],"فِى":["in/within"]}},"83:7:6":{"w":"سِجِّينٍ","m":"a deep prison (being described in كِتٰبَ الفُجَّارِ)","p":{"سِجِّين":["a deep prison"],"ٍ":["being described"]}},"83:8:1":{"w":"وَمَآ","m":"and what (asking about سِجِّينٌ)","p":{"وَ":["and"],"مَآ":["what"]}},"83:8:2":{"w":"أَدْرَىٰكَ","m":"made you know","p":{"أَ":["made"],"دْرَىٰ":["know"],"كَ":["you"]}},"83:8:3":{"w":"مَا","m":"what","p":{"مَا":["what"]}},"83:8:4":{"w":"سِجِّينٌ","m":"a record (of evil deeds)","p":{"سِجِّين":["a record (of evil deeds)"],"ٌ":["a"]}},"83:9:1":{"w":"كِتٰبٌ","m":"a book (subject of مَّرْقُومٌ)","p":{"كِتٰب":["book"],"ٌ":["a"]}},"83:9:2":{"w":"مَّرْقُومٌ","m":"a definitely marked/numbered (record)","p":{"مَّ":["definitely"],"رْقُوم":["marked/numbered"],"ٌ":["a"]}},"83:10:1":{"w":"وَيْلٌ","m":"woe/destruction! (threatening those who deny)","p":{"وَيْل":["woe/destruction"],"ٌ":["!"]}},"83:10:2":{"w":"يَوْمَئِذٍ","m":"on that day","p":{"يَوْمَ":["day","on"],"ئِذٍ":["that"]}},"83:10:3":{"w":"لِّلْمُكَذِّبِينَ","m":"for/to the ones who repeatedly deny","p":{"لِّلْ":["for/to","the"],"مُكَذِّبِ":["ones who repeatedly deny"],"ينَ":["ones who"]}},"83:11:2":{"w":"يُكَذِّبُونَ","m":"they strongly deny/reject (referring to those who deny the Day of Judgment)","p":{"يُ":["they"],"كَذِّبُ":["strongly deny/reject"],"ونَ":["they"]}},"83:11:3":{"w":"بِيَوْمِ","m":"by/in the day (possessed by الدِّينِ)","p":{"بِ":["by/in"],"يَوْمِ":["day"],"ِ":["the"]}},"83:11:4":{"w":"ٱلدِّينِ","m":"the judgment/religion (object of Day of)","p":{"ٱل":["the"],"دِّين":["judgment/religion"],"ِ":["of"]}},"83:12:1":{"w":"وَمَا","m":"and what/that which (subject of يُكَذِّبُ)","p":{"وَ":["and"],"مَا":["what/that which"]}},"83:12:2":{"w":"يُكَذِّبُ","m":"he denies/rejects (something) (subject of مَا)","p":{"يُ":["he"],"كَذِّبُ":["denies/rejects (something)"]}},"83:12:3":{"w":"بِهِۦٓ","m":"with it/by it (acted on by يُكَذِّبُ)","p":{"بِ":["with/by"],"هِۦٓ":["it"]}},"83:12:4":{"w":"إِلَّا","m":"except (connecting to كُلُّ مُعْتَدٍ أَثِيمٍ)","p":{"إِلَّا":["except"]}},"83:12:5":{"w":"كُلُّ","m":"every (transgressor/أَثِيمٍ)","p":{"كُلُّ":["every"]}},"83:12:6":{"w":"مُعْتَدٍ","m":"transgressor (describes someone in كُلُّ/every)","p":{"مُ":["transgressor"],"عْتَ":["transgressor"],"دٍ":["transgressor"]}},"83:12:7":{"w":"أَثِيمٍ","m":"a sinful one (describing مُعْتَدٍ - transgressor)","p":{"أَثِيم":["a sinful one"],"ٍ":["(describing مُعْتَدٍ - transgressor)"]}},"83:13:1":{"w":"إِذَا","m":"when (referring to something that will happen in the future)","p":{"إِ":["when"],"ذَا":["(in the future)"]}},"83:13:2":{"w":"تُتْلَىٰ","m":"it is being recited","p":{"تُ":["it is"],"تْلَ":["recited"],"ىٰ":["being"]}},"83:13:3":{"w":"عَلَيْهِ","m":"upon him (object of تُتْلَىٰ/are recited)","p":{"عَلَيْ":["upon"],"هِ":["him"]}},"83:13:4":{"w":"ءَايٰتُنَا","m":"our signs, our verses (that are being recited)","p":{"ءَايٰتُ":["signs, verses"],"نَا":["our"]}},"83:13:5":{"w":"قَالَ","m":"he said","p":{"قَا":["he"],"لَ":["said"]}},"83:13:6":{"w":"أَسٰطِيرُ","m":"tales/legends (subject of قَالَ)","p":{"أَ":[],"سٰطِير":["tales/legends"],"ُ":["(subject of قَالَ)"]}},"83:13:7":{"w":"ٱلْأَوَّلِينَ","m":"the ancient ones (possessed by أَسٰطِيرُ)","p":{"ٱلْ":["the"],"أَوَّلِ":["ancient"],"ينَ":["ones"]}},"83:14:1":{"w":"كَلَّا","m":"No indeed! (strongly rejecting what came before)","p":{"كَلَّا":["No indeed! (strongly rejecting what came before)"]}},"83:14:2":{"w":"بَلْ","m":"No! Rather...","p":{"بَ":["No!"],"لْ":["Rather..."]}},"83:14:3":{"w":"رَانَ","m":"he rusted/covered (something)","p":{"رَا":["rusted/covered"],"نَ":["he"]}},"83:14:4":{"w":"عَلَىٰ","m":"upon/over (connected to قُلُوبِهِم - their hearts)","p":{"عَلَىٰ":["upon/over"]}},"83:14:6":{"w":"مَّا","m":"what (they) (connects to كَانُوا يَكْسِبُونَ - they used to earn)","p":{"مَّا":["what"],"ا":["they"]}},"83:14:7":{"w":"كَانُوا","m":"they were (subject of يَكْسِبُونَ)","p":{"كَان":["were"],"ُو":["they"],"ا":["they"]}},"83:14:8":{"w":"يَكْسِبُونَ","m":"they are earning/gaining","p":{"يَ":["they are"],"كْسِبُ":["earning/gaining"],"ونَ":["they"]}},"83:15:1":{"w":"كَلَّآ","m":"No indeed! (strongly rejecting what was mentioned before)","p":{"كَلَّآ":["No indeed! (strongly rejecting what was mentioned before)"]}},"83:15:2":{"w":"إِنَّهُمْ","m":"indeed they","p":{"إِنَّ":["indeed"],"هُمْ":["they"]}},"83:15:3":{"w":"عَن","m":"away from","p":{"عَ":["away"],"ن":["from"]}},"83:15:4":{"w":"رَّبِّهِمْ","m":"their Lord","p":{"رَّبِّ":["Lord"],"هِمْ":["their"]}},"83:15:5":{"w":"يَوْمَئِذٍ","m":"on that day (when they will be blocked from their Lord)","p":{"يَوْمَ":["day"],"ئِذٍ":["on that"]}},"83:15:6":{"w":"لَّمَحْجُوبُونَ","m":"surely they are blocked/prevented (from their Lord on that Day)","p":{"لَّ":["surely"],"مَحْجُوبُ":["blocked/prevented"],"ونَ":["they are"]}},"83:16:1":{"w":"ثُمَّ","m":"then (after a delay/with emphasis)","p":{"ثُ":["then"],"مَّ":["with delay/emphasis"]}},"83:16:2":{"w":"إِنَّهُمْ","m":"indeed they (will burn)","p":{"إِنَّ":["indeed"],"هُمْ":["they"]}},"83:16:3":{"w":"لَصَالُوا","m":"surely they will burn/enter fire","p":{"لَ":["surely"],"صَا":["burn/enter"],"لُ":["will"],"وا":["they"]}},"83:16:4":{"w":"ٱلْجَحِيمِ","m":"the hellfire (being described in this ayah)","p":{"ٱلْ":["the"],"جَحِيمِ":["hellfire (being described in this ayah)"]}},"83:17:1":{"w":"ثُمَّ","m":"then (connects to يُقَالُ - it will be said)","p":{"ثُمَّ":["then"]}},"83:17:2":{"w":"يُقَالُ","m":"it is said (introducing what follows)","p":{"يُ":["it"],"قَال":["is said"],"ُ":["(introducing what follows)"]}},"83:17:3":{"w":"هٰذا","m":"this (being pointed to in يُقَالُ - it is said)","p":{"هٰ":["this"],"ذا":["(being pointed to in يُقَالُ - it is said)"]}},"83:17:4":{"w":"ٱلَّذِى","m":"who/which/that (referring to 'this' that you were told about)","p":{"ٱلَّذِى":["who/which/that (referring to 'this' that you were told about)"]}},"83:17:5":{"w":"كُنتُم","m":"you all were","p":{"كُن":["were"],"تُ":["you"],"م":["all"]}},"83:17:6":{"w":"بِهِۦ","m":"with it/by it (object of تُكَذِّبُونَ)","p":{"بِ":["with/by"],"هِۦ":["it"]}},"83:18:1":{"w":"كَلَّآ","m":"No indeed! (strongly rejecting what was mentioned before)","p":{"كَلَّآ":["No indeed! (strongly rejecting what was mentioned before)"]}},"83:18:2":{"w":"إِنَّ","m":"indeed/truly (emphasizing كِتٰبَ ٱلْأَبْرَارِ)","p":{"إِنَّ":["indeed/truly"]}},"83:18:3":{"w":"كِتٰبَ","m":"book (object of إِنَّ)","p":{"كِتٰبَ":["book"]}},"83:18:4":{"w":"ٱلْأَبْرَارِ","m":"the righteous ones","p":{"ٱلْ":["the"],"أَبْرَارِ":["righteous ones"]}},"83:18:5":{"w":"لَفِى","m":"surely in (connected to عِلِّيِّينَ)","p":{"لَ":["surely"],"فِى":["in"]}},"83:18:6":{"w":"عِلِّيِّينَ","m":"highest places (in heaven)","p":{"عِلِّيِّ":["highest places"],"ينَ":["(in heaven)"]}},"83:19:1":{"w":"وَمَآ","m":"and what (connects to أَدْرَىٰكَ)","p":{"وَ":["and"],"مَآ":["what"]}},"83:19:2":{"w":"أَدْرَىٰكَ","m":"made you know (object of وَمَآ)","p":{"أَ":["made"],"دْرَىٰ":["know"],"كَ":["you"]}},"83:19:3":{"w":"مَا","m":"what","p":{"مَا":["what"]}},"83:19:4":{"w":"عِلِّيُّونَ","m":"the highest ones (referring to the record books of the righteous)","p":{"عِلِّيُّ":["the highest"],"ونَ":["ones"]}},"83:20:1":{"w":"كِتٰبٌ","m":"a book (described by مَّرْقُومٌ - inscribed)","p":{"كِتٰب":["book"],"ٌ":["a"]}},"83:20:2":{"w":"مَّرْقُومٌ","m":"a definitely written/recorded thing (describing كِتٰبٌ)","p":{"مَّ":["definitely"],"رْقُو":["written/recorded"],"مٌ":["thing"]}},"83:21:1":{"w":"يَشْهَدُهُ","m":"he witnesses it (the record book that المقربون witness)","p":{"يَ":["he"],"شْهَدُ":["witnesses"],"هُ":["it"]}},"83:21:2":{"w":"ٱلْمُقَرَّبُونَ","m":"the ones who are brought near (witnesses of يَشْهَدُهُ)","p":{"ٱلْ":["the"],"مُ":["ones who are"],"قَرَّبُ":["brought near"],"ونَ":["ones"]}},"83:22:1":{"w":"إِنَّ","m":"indeed/truly (emphasizing ٱلْأَبْرَارَ)","p":{"إِنَّ":["indeed/truly"]}},"83:22:2":{"w":"ٱلْأَبْرَارَ","m":"the righteous ones (object of إِنَّ)","p":{"ٱلْ":["the"],"أَبْرَارَ":["righteous ones (object of إِنَّ)"]}},"83:22:3":{"w":"لَفِى","m":"surely in (connects نَعِيمٍ to ٱلْأَبْرَارَ)","p":{"لَ":["surely/truly"],"فِى":["in"]}},"83:22:4":{"w":"نَعِيمٍ","m":"of paradise/bliss (possessed by the righteous)","p":{"نَعِيم":["paradise/bliss"],"ٍ":["of"]}},"83:23:1":{"w":"عَلَى","m":"upon/on (looking at يَنظُرُونَ)","p":{"عَلَى":["upon/on"]}},"83:23:2":{"w":"ٱلْأَرَآئِكِ","m":"the ornate couches (being reclined upon)","p":{"ٱلْ":["the"],"أَرَآئِكِ":["ornate couches (being reclined upon)"]}},"83:23:3":{"w":"يَنظُرُونَ","m":"they look/watch (referring to the blessed people on thrones mentioned in عَلَى ٱلْأَرَآئِكِ)","p":{"يَ":["they"],"نظُرُ":["look/watch"],"ونَ":["they"]}},"83:24:1":{"w":"تَعْرِفُ","m":"you/she recognize(s)","p":{"تَ":["you/she"],"عْرِفُ":["recognize(s)"]}},"83:24:2":{"w":"فِى","m":"in (connects تَعْرِفُ to وُجُوهِهِمْ)","p":{"فِى":["in"]}},"83:24:3":{"w":"وُجُوهِهِمْ","m":"their faces (object of تَعْرِفُ)","p":{"وُجُوهِ":["faces"],"هِمْ":["their"]}},"83:24:4":{"w":"نَضْرَةَ","m":"radiance/brightness (that you see on وُجُوهِهِمْ their faces)","p":{"نَضْرَ":["radiance/brightness"],"ةَ":["(that you see on وُجُوهِهِمْ their faces)"]}},"83:24:5":{"w":"ٱلنَّعِيمِ","m":"the bliss (that the righteous experience)","p":{"ٱل":["the"],"نَّعِيمِ":["bliss (that the righteous experience)"]}},"83:25:1":{"w":"يُسْقَوْنَ","m":"they are given drink (of رَّحِيقٍ)","p":{"يُ":["they"],"سْقَ":["given drink"],"وْنَ":["are"]}},"83:25:2":{"w":"مِن","m":"from (connecting يُسْقَوْنَ with رَّحِيقٍ)","p":{"مِن":["from"]}},"83:25:3":{"w":"رَّحِيقٍ","m":"of pure wine (object of يُسْقَوْنَ - they are given to drink)","p":{"رَّحِيق":["pure wine"],"ٍ":["of"]}},"83:25:4":{"w":"مَّخْتُومٍ","m":"of something completely sealed","p":{"مَّ":["completely"],"خْتُوم":["sealed"],"ٍ":["of something"]}},"83:26:1":{"w":"خِتٰمُهُۥ","m":"its seal (subject of مِسْكٌ)","p":{"خِتٰمُ":["seal"],"هُۥ":["its"]}},"83:26:2":{"w":"مِسْكٌ","m":"musk (as the main subject)","p":{"مِسْ":["musk"],"كٌ":["(as the main subject)"]}},"83:26:3":{"w":"وَفِى","m":"and in (connects to مِسْكٌ)","p":{"وَ":["and"],"فِى":["in"]}},"83:26:4":{"w":"ذٰلِكَ","m":"that (specific thing)","p":{"ذٰ":["that"],"لِ":["specific"],"كَ":["thing"]}},"83:26:5":{"w":"فَلْيَتَنَافَسِ","m":"so let him compete with others","p":{"فَ":["so"],"لْ":["let"],"يَ":["him"],"تَنَافَسِ":["compete with others"]}},"83:26:6":{"w":"ٱلْمُتَنٰفِسُونَ","m":"the ones who compete with each other (plural men)","p":{"ٱلْ":["the"],"مُتَ":["ones who"],"نٰفِسُ":["compete with each other"],"ونَ":["(plural men)"]}},"83:27:2":{"w":"مِن","m":"from (source of تَسْنِيمٍ)","p":{"مِ":["from"],"ن":["(source)"]}},"83:27:3":{"w":"تَسْنِيمٍ","m":"of/from Tasneem (after مِن)","p":{"تَسْنِيم":["Tasneem"],"ٍ":["of/from"]}},"83:28:1":{"w":"عَيْنًا","m":"a spring (object of يَشْرَبُ - drinks from)","p":{"عَيْن":["spring"],"ًا":["a"]}},"83:28:3":{"w":"بِهَا","m":"with/by it (feminine)","p":{"بِ":["with/by"],"هَا":["it (feminine)"]}},"83:28:4":{"w":"ٱلْمُقَرَّبُونَ","m":"the ones who are drawn especially near (referring to special ranks of angels and righteous people)","p":{"ٱلْ":["the"],"مُ":["ones who are"],"قَرَّ":["drawn especially near"],"بُونَ":["ones who are"]}},"83:29:1":{"w":"إِنَّ","m":"indeed/verily (emphasizes that ٱلَّذِينَ أَجْرَمُوا۟ were mocking)","p":{"إِنَّ":["indeed/verily"]}},"83:29:2":{"w":"ٱلَّذِينَ","m":"those who (referring to the criminals mentioned in أَجْرَمُوا۟)","p":{"ٱلَّذِي":["those who"],"نَ":["(referring to the criminals mentioned in أَجْرَمُوا۟)"]}},"83:29:3":{"w":"أَجْرَمُوا۟","m":"they became criminal/sinful","p":{"أَ":["became"],"جْرَمُ":["criminal/sinful"],"وا":["they"]}},"83:29:4":{"w":"كَانُوا","m":"they were","p":{"كَان":["were"],"وا":["they"]}},"83:29:5":{"w":"مِنَ","m":"from (connects to ٱلَّذِينَ)","p":{"مِنَ":["from"]}},"83:29:7":{"w":"ءَامَنُوا۟","m":"they believed (subject of يَضْحَكُونَ - they laugh)","p":{"ءَامَن":["believed"],"ُوا":["they"]}},"83:29:8":{"w":"يَضْحَكُونَ","m":"they laugh","p":{"يَ":["they"],"ضْحَكُ":["laugh"],"ونَ":["they"]}},"83:30:1":{"w":"وَإِذَا","m":"and when (connecting to what happened before)","p":{"وَ":["and"],"إِذَا":["when"]}},"83:30:2":{"w":"مَرُّوا۟","m":"they passed by","p":{"مَرُّ":["passed by"],"وا":["they"]}},"83:30:3":{"w":"بِهِمْ","m":"by/with them (who they wink at)","p":{"بِ":["by/with"],"هِمْ":["them"]}},"83:30:4":{"w":"يَتَغَامَزُونَ","m":"they wink at each other","p":{"يَ":["they"],"تَ":["at each other"],"غَامَزُ":["wink"],"ونَ":["they"]}},"83:31:1":{"w":"وَإِذَا","m":"and when (connects to what happened before)","p":{"وَ":["and"],"إِذَا":["when (connects to what happened before)"]}},"83:31:2":{"w":"اِنْقَلَبُوا","m":"they turned themselves/returned (to أَهْلِهِمُ their families)","p":{"اِنْ":["turned themselves/returned"],"قَلَبُ":["turned themselves/returned"],"وا":["they"]}},"83:31:3":{"w":"إِلَىٰٓ","m":"to/towards (connecting to أَهْلِهِمُ)","p":{"إِلَىٰٓ":["to/towards"]}},"83:31:4":{"w":"أَهْلِهِمُ","m":"their family (referring to those who returned in انقَلَبُوٓا۟)","p":{"أَهْلِ":["family"],"هِمُ":["their"]}},"83:31:5":{"w":"اِنْقَلَبُوا","m":"they turned themselves back (to أَهْلِهِمُ their families)","p":{"اِنْ":["turned themselves"],"قَلَبُ":["back"],"وا":["they"]}},"83:31:6":{"w":"فَكِهِينَ","m":"happy ones (describing a group of men)","p":{"فَكِهِ":["happy"],"ينَ":["ones (describing a group of men)"]}},"83:32:1":{"w":"وَإِذَا","m":"and when","p":{"وَ":["and"],"إِذَا":["when"]}},"83:32:2":{"w":"رَأَوْهُمْ","m":"they saw them","p":{"رَأَوْ":["they saw"],"هُمْ":["them"]}},"83:32:3":{"w":"قَالُوٓا۟","m":"they said (speaking about هٰٓؤُلَآءِ/these people)","p":{"قَال":["said"],"ُو":["they"],"ٓا۟":["(speaking about هٰٓؤُلَآءِ/these people)"]}},"83:32:4":{"w":"إِنَّ","m":"indeed/certainly (emphasizes 'these people are astray')","p":{"إِ":["indeed"],"نَّ":["certainly"]}},"83:32:5":{"w":"هٰٓؤُلَآءِ","m":"these ones (who are being spoken about)","p":{"هٰٓؤُلَآءِ":["these ones (who are being spoken about)"]}},"83:32:6":{"w":"لَضَآلُّونَ","m":"surely they are astray","p":{"لَ":["surely"],"ضَآلُّ":["astray"],"ونَ":["they are"]}},"83:33:1":{"w":"وَمَآ","m":"and they were not (negating أُرْسِلُوا۟)","p":{"وَ":["and"],"مَآ":["they were not"]}},"83:33:2":{"w":"أُرْسِلُوا۟","m":"they were sent (subject of the sentence)","p":{"أُ":["were"],"رْسِلُ":["sent"],"وا۟":["they"]}},"83:33:3":{"w":"عَلَيْهِمْ","m":"upon them","p":{"عَلَيْ":["upon"],"هِمْ":["them"]}},"83:33:4":{"w":"حَافِظِينَ","m":"guardians/protectors (in accusative case)","p":{"حَافِظ":["guardians/protectors"],"ِينَ":["(in accusative case)"]}},"83:34:1":{"w":"فَٱلْيَوْمَ","m":"so today (when يَضْحَكُونَ/they laugh happens)","p":{"فَ":["so"],"ٱلْ":[""],"يَوْمَ":["today"]}},"83:34:2":{"w":"ٱلَّذِينَ","m":"those who (plural, referring to ٱلْكُفَّارِ)","p":{"ٱلَّذِي":["those who"],"نَ":["plural"]}},"83:34:3":{"w":"ءَامَنُوا۟","m":"they believed","p":{"ءَامَن":["believed"],"ُوا":["they"]}},"83:34:4":{"w":"مِنَ","m":"from (connected to ٱلْكُفَّارِ)","p":{"مِنَ":["from"]}},"83:34:5":{"w":"ٱلْكُفَّارِ","m":"of/from the disbelievers (after مِنَ)","p":{"ٱلْ":["the"],"كُفَّارِ":["disbelievers","of/from"],"كُفَّار":["disbelievers"],"ِ":["of/from"]}},"83:34:6":{"w":"يَضْحَكُونَ","m":"they are laughing","p":{"يَ":["are"],"ضْحَكُ":["laughing"],"ونَ":["they"]}},"83:35:1":{"w":"عَلَى","m":"upon/on (the ٱلْأَرَآئِكِ - couches)","p":{"عَلَى":["upon/on"]}},"83:35:2":{"w":"ٱلْأَرَآئِكِ","m":"on the decorated couches/thrones (in relation to عَلَى)","p":{"ٱلْ":["the"],"أَرَآئِكِ":["decorated couches/thrones"]}},"83:35:3":{"w":"يَنظُرُونَ","m":"they are looking (referring to the disbelievers reclining on couches mentioned in عَلَى ٱلْأَرَآئِكِ)","p":{"يَ":["are"],"نظُرُ":["looking"],"ونَ":["they"]}},"83:36:1":{"w":"هَلْ","m":"Have (they been)","p":{"هَلْ":["Have (they been)"]}},"83:36:2":{"w":"ثُوِّبَ","m":"was rewarded","p":{"ثُوِّ":["reward"],"بَ":["was"]}},"83:36:3":{"w":"ٱلْكُفَّارُ","m":"the rejecters (of truth) (subject of ثُوِّبَ)","p":{"ٱلْ":["the"],"كُفَّارُ":["rejecters (of truth)"],"ُ":["(subject of ثُوِّبَ)"]}},"83:36:4":{"w":"مَا","m":"what","p":{"مَا":["what"]}},"83:36:5":{"w":"كَانُوا","m":"they were (subject of يَفْعَلُونَ)","p":{"كَان":["were"],"ُو":["they"],"ا":["they"]}},"83:36:6":{"w":"يَفْعَلُونَ","m":"they do/are doing","p":{"يَ":["do/are doing"],"فْعَلُ":["do/are doing"],"ونَ":["they"]}}}